{"customer_id": "C9", "basket": [{"product_id": "P22", "price": 16}, {"product_id": "P28", "price": 1521}], "date_of_purchase": "2018-12-21 10:31:00"}
{"customer_id": "C10", "basket": [{"product_id": "P22", "price": 1456}, {"product_id": "P29", "price": 1958}, {"product_id": "P24", "price": 956}], "date_of_purchase": "2018-12-21 15:44:00"}
{"customer_id": "C17", "basket": [{"product_id": "P34", "price": 1689}], "date_of_purchase": "2018-12-21 04:48:00"}
{"customer_id": "C32", "basket": [{"product_id": "P63", "price": 1277}], "date_of_purchase": "2018-12-21 19:35:00"}
{"customer_id": "C34", "basket": [{"product_id": "P39", "price": 1293}, {"product_id": "P35", "price": 1827}], "date_of_purchase": "2018-12-21 16:18:00"}
{"customer_id": "C37", "basket": [{"product_id": "P62", "price": 755}, {"product_id": "P64", "price": 525}], "date_of_purchase": "2018-12-21 16:40:00"}
{"customer_id": "C41", "basket": [{"product_id": "P29", "price": 1258}], "date_of_purchase": "2018-12-21 12:53:00"}
{"customer_id": "C44", "basket": [{"product_id": "P49", "price": 1538}], "date_of_purchase": "2018-12-21 12:05:00"}
{"customer_id": "C45", "basket": [{"product_id": "P08", "price": 969}, {"product_id": "P09", "price": 1265}, {"product_id": "P08", "price": 528}], "date_of_purchase": "2018-12-21 08:20:00"}
{"customer_id": "C53", "basket": [{"product_id": "P45", "price": 460}, {"product_id": "P44", "price": 291}, {"product_id": "P43", "price": 425}], "date_of_purchase": "2018-12-21 03:31:00"}
{"customer_id": "C55", "basket": [{"product_id": "P59", "price": 1804}, {"product_id": "P52", "price": 156}], "date_of_purchase": "2018-12-21 03:36:00"}
{"customer_id": "C56", "basket": [{"product_id": "P61", "price": 240}, {"product_id": "P64", "price": 1342}, {"product_id": "P63", "price": 1853}], "date_of_purchase": "2018-12-21 16:27:00"}
{"customer_id": "C64", "basket": [{"product_id": "P33", "price": 334}], "date_of_purchase": "2018-12-21 19:41:00"}
{"customer_id": "C67", "basket": [{"product_id": "P39", "price": 1575}], "date_of_purchase": "2018-12-21 10:17:00"}
{"customer_id": "C72", "basket": [{"product_id": "P35", "price": 986}], "date_of_purchase": "2018-12-21 17:35:00"}
{"customer_id": "C75", "basket": [{"product_id": "P38", "price": 1982}, {"product_id": "P38", "price": 849}, {"product_id": "P38", "price": 453}], "date_of_purchase": "2018-12-21 12:03:00"}
{"customer_id": "C77", "basket": [{"product_id": "P16", "price": 1572}], "date_of_purchase": "2018-12-21 05:44:00"}
{"customer_id": "C96", "basket": [{"product_id": "P48", "price": 1556}], "date_of_purchase": "2018-12-21 17:33:00"}
{"customer_id": "C97", "basket": [{"product_id": "P60", "price": 1394}], "date_of_purchase": "2018-12-21 18:07:00"}
{"customer_id": "C99", "basket": [{"product_id": "P37", "price": 901}, {"product_id": "P37", "price": 1454}], "date_of_purchase": "2018-12-21 17:49:00"}
{"customer_id": "C100", "basket": [{"product_id": "P18", "price": 1214}], "date_of_purchase": "2018-12-21 13:36:00"}
{"customer_id": "C103", "basket": [{"product_id": "P53", "price": 1798}, {"product_id": "P48", "price": 710}, {"product_id": "P54", "price": 239}], "date_of_purchase": "2018-12-21 11:45:00"}
{"customer_id": "C114", "basket": [{"product_id": "P58", "price": 690}], "date_of_purchase": "2018-12-21 15:52:00"}
{"customer_id": "C119", "basket": [{"product_id": "P28", "price": 773}, {"product_id": "P25", "price": 206}, {"product_id": "P28", "price": 94}], "date_of_purchase": "2018-12-21 04:08:00"}
{"customer_id": "C125", "basket": [{"product_id": "P35", "price": 936}, {"product_id": "P40", "price": 815}], "date_of_purchase": "2018-12-21 07:06:00"}
{"customer_id": "C128", "basket": [{"product_id": "P62", "price": 946}, {"product_id": "P61", "price": 304}, {"product_id": "P61", "price": 1425}], "date_of_purchase": "2018-12-21 03:41:00"}
{"customer_id": "C129", "basket": [{"product_id": "P29", "price": 1681}, {"product_id": "P22", "price": 1079}], "date_of_purchase": "2018-12-21 07:28:00"}
{"customer_id": "C132", "basket": [{"product_id": "P27", "price": 1862}, {"product_id": "P28", "price": 1248}, {"product_id": "P27", "price": 1885}], "date_of_purchase": "2018-12-21 20:19:00"}
{"customer_id": "C134", "basket": [{"product_id": "P58", "price": 329}, {"product_id": "P57", "price": 961}, {"product_id": "P59", "price": 1190}], "date_of_purchase": "2018-12-21 22:04:00"}
