{"customer_id": "C4", "basket": [{"product_id": "P36", "price": 725}], "date_of_purchase": "2018-12-31 04:25:00"}
{"customer_id": "C6", "basket": [{"product_id": "P31", "price": 292}, {"product_id": "P31", "price": 145}], "date_of_purchase": "2018-12-31 15:48:00"}
{"customer_id": "C11", "basket": [{"product_id": "P22", "price": 1078}], "date_of_purchase": "2018-12-31 14:18:00"}
{"customer_id": "C18", "basket": [{"product_id": "P35", "price": 334}, {"product_id": "P40", "price": 1518}, {"product_id": "P37", "price": 1034}], "date_of_purchase": "2018-12-31 04:15:00"}
{"customer_id": "C26", "basket": [{"product_id": "P17", "price": 1990}, {"product_id": "P20", "price": 1574}], "date_of_purchase": "2018-12-31 07:37:00"}
{"customer_id": "C37", "basket": [{"product_id": "P05", "price": 1662}, {"product_id": "P06", "price": 1852}, {"product_id": "P10", "price": 675}], "date_of_purchase": "2018-12-31 08:04:00"}
{"customer_id": "C42", "basket": [{"product_id": "P22", "price": 389}, {"product_id": "P24", "price": 1137}], "date_of_purchase": "2018-12-31 14:41:00"}
{"customer_id": "C43", "basket": [{"product_id": "P23", "price": 1954}], "date_of_purchase": "2018-12-31 10:20:00"}
{"customer_id": "C50", "basket": [{"product_id": "P30", "price": 386}], "date_of_purchase": "2018-12-31 17:57:00"}
{"customer_id": "C61", "basket": [{"product_id": "P20", "price": 1373}, {"product_id": "P14", "price": 1487}], "date_of_purchase": "2018-12-31 08:02:00"}
{"customer_id": "C63", "basket": [{"product_id": "P35", "price": 676}], "date_of_purchase": "2018-12-31 05:00:00"}
{"customer_id": "C69", "basket": [{"product_id": "P62", "price": 1178}], "date_of_purchase": "2018-12-31 18:35:00"}
{"customer_id": "C79", "basket": [{"product_id": "P56", "price": 1767}, {"product_id": "P49", "price": 861}], "date_of_purchase": "2018-12-31 20:58:00"}
{"customer_id": "C81", "basket": [{"product_id": "P10", "price": 1369}], "date_of_purchase": "2018-12-31 14:00:00"}
{"customer_id": "C83", "basket": [{"product_id": "P35", "price": 242}, {"product_id": "P39", "price": 1224}, {"product_id": "P37", "price": 1256}], "date_of_purchase": "2018-12-31 05:45:00"}
{"customer_id": "C85", "basket": [{"product_id": "P56", "price": 950}], "date_of_purchase": "2018-12-31 09:25:00"}
{"customer_id": "C87", "basket": [{"product_id": "P62", "price": 482}, {"product_id": "P61", "price": 299}], "date_of_purchase": "2018-12-31 22:43:00"}
{"customer_id": "C101", "basket": [{"product_id": "P47", "price": 1580}, {"product_id": "P57", "price": 1382}, {"product_id": "P60", "price": 605}], "date_of_purchase": "2018-12-31 15:57:00"}
{"customer_id": "C102", "basket": [{"product_id": "P04", "price": 1718}, {"product_id": "P04", "price": 1249}, {"product_id": "P08", "price": 1316}], "date_of_purchase": "2018-12-31 13:33:00"}
{"customer_id": "C103", "basket": [{"product_id": "P52", "price": 1649}, {"product_id": "P60", "price": 1766}, {"product_id": "P50", "price": 511}], "date_of_purchase": "2018-12-31 22:46:00"}
{"customer_id": "C111", "basket": [{"product_id": "P26", "price": 738}, {"product_id": "P26", "price": 1037}, {"product_id": "P28", "price": 520}], "date_of_purchase": "2018-12-31 18:11:00"}
{"customer_id": "C115", "basket": [{"product_id": "P36", "price": 1009}, {"product_id": "P38", "price": 1889}, {"product_id": "P37", "price": 419}], "date_of_purchase": "2018-12-31 19:24:00"}
{"customer_id": "C117", "basket": [{"product_id": "P47", "price": 1045}, {"product_id": "P60", "price": 609}, {"product_id": "P59", "price": 521}], "date_of_purchase": "2018-12-31 15:26:00"}
{"customer_id": "C118", "basket": [{"product_id": "P41", "price": 967}, {"product_id": "P51", "price": 659}], "date_of_purchase": "2018-12-31 09:50:00"}
{"customer_id": "C123", "basket": [{"product_id": "P38", "price": 1028}, {"product_id": "P36", "price": 1168}, {"product_id": "P37", "price": 1384}], "date_of_purchase": "2018-12-31 17:16:00"}
{"customer_id": "C128", "basket": [{"product_id": "P05", "price": 343}], "date_of_purchase": "2018-12-31 04:15:00"}
